$PLACEHOLDER
MANIFEST.in
README.rst
setup.py
libqrencode/__init__.py
libqrencode/ffi_build.py
libqrencode/qrencode-3.4.4-noifdefs.h
libqrencode_cffi.egg-info/PKG-INFO
libqrencode_cffi.egg-info/SOURCES.txt
libqrencode_cffi.egg-info/dependency_links.txt
libqrencode_cffi.egg-info/requires.txt
libqrencode_cffi.egg-info/top_level.txt
test/test_libqrencode.py