Metadata-Version: 1.0
Name: libqrencode-cffi
Version: 0.1.1
Summary: Fast, robust, and less incomplete cffi-based bindings for libqrencode (Py2, Py3, and PyPy)
Home-page: https://github.com/wolever/libqrencode-cffi
Author: David Wolever
Author-email: david@wolever.net
License: UNKNOWN
Platform: UNKNOWN
Classifier: Development Status :: 4 - Beta
Classifier: Programming Language :: Python :: 2
Classifier: Programming Language :: Python :: 3
Classifier: Programming Language :: Python :: Implementation :: PyPy
Classifier: License :: OSI Approved :: BSD License
